<?xml version="1.0" encoding="utf-8" ?>
<dwsync>
<file name="curvedLines.js" server="chi-node59.websitehostserver.net/public_html/app/" local="132457947930000000" remote="132457947930000000" Dst="2" />
<file name="jquery.flot.categories.min.js" server="chi-node59.websitehostserver.net/public_html/app/" local="132457947930000000" remote="132457947930000000" Dst="2" />
<file name="jquery.flot.js" server="chi-node59.websitehostserver.net/public_html/app/" local="132457947930000000" remote="132457947930000000" Dst="2" />
<file name="jquery.flot.min.js" server="chi-node59.websitehostserver.net/public_html/app/" local="132457947930000000" remote="132457947930000000" Dst="2" />
<file name="jquery.flot.pie.min.js" server="chi-node59.websitehostserver.net/public_html/app/" local="132457947930000000" remote="132457947930000000" Dst="2" />
<file name="jquery.flot.resize.min.js" server="chi-node59.websitehostserver.net/public_html/app/" local="132457947930000000" remote="132457947930000000" Dst="2" />
<file name="jquery.flot.time.min.js" server="chi-node59.websitehostserver.net/public_html/app/" local="132457947930000000" remote="132457947930000000" Dst="2" />
<file name="jquery.flot.tooltip.min.js" server="chi-node59.websitehostserver.net/public_html/app/" local="132457947930000000" remote="132457947930000000" Dst="2" />
</dwsync>